zoresearch/__init__.py
zoresearch/gui.py
zoresearch/main.py
zoresearch/source.py
zoresearch/sources_db.py
zoresearch/icon/__init__.py
zoresearch-0.1.1.dist-info/LICENSE
zoresearch-0.1.1.dist-info/METADATA
zoresearch-0.1.1.dist-info/WHEEL
zoresearch-0.1.1.dist-info/top_level.txt
zoresearch-0.1.1.dist-info/RECORD
