Metadata-Version: 2.1
Name: zoresearch
Version: 0.1.1
Summary: Interactive research application built on top of Zotero citation manager
Author-email: Daniel Waldroop <dlwaldroop@gmail.com>
License: Copyright (c) 2018 The Python Packaging Authority        
Project-URL: Homepage, https://github.com/dlw-github/zoresearch
Classifier: Programming Language :: Python :: 3
Classifier: License :: OSI Approved :: MIT License
Classifier: Operating System :: OS Independent
Requires-Python: >=3.7
License-File: LICENSE
